chitram/__init__.py
chitram/branding.py
chitram/generator.py
chitram-0.1.0.dist-info/licenses/LICENSE
chitram-0.1.0.dist-info/METADATA
chitram-0.1.0.dist-info/WHEEL
chitram-0.1.0.dist-info/top_level.txt
chitram-0.1.0.dist-info/RECORD
