Metadata-Version: 2.4
Name: chitram
Version: 0.1.0
Summary: 🎨 Chitram: Generate images from text prompts using AI
Author: Aman Mishra
Author-email: jarvisbyaman@gmail.com
License: MIT
Project-URL: YouTube, https://www.youtube.com/channel/UCuYpMYOiuQyGgdM9LXupLEg
Project-URL: Telegram, https://t.me/jarvisbyamanchannel
Classifier: Programming Language :: Python :: 3
Classifier: License :: OSI Approved :: MIT License
Classifier: Operating System :: OS Independent
Requires-Python: >=3.7
License-File: LICENSE
Requires-Dist: requests
Requires-Dist: Pillow
Requires-Dist: rich
Dynamic: author
Dynamic: author-email
Dynamic: classifier
Dynamic: description
Dynamic: description-content-type
Dynamic: license
Dynamic: license-file
Dynamic: project-url
Dynamic: requires-dist
Dynamic: requires-python
Dynamic: summary
